[
  {
    "id": 1,
    "image": "../assets/skincare/skincare1.jpeg"
  },
  {
    "id": 2,
    "image": "../assets/skincare/skincare2.jpeg"
  },
  {
    "id": 3,
    "image": "../assets/skincare/skincare3.jpeg"
  },
  {
    "id": 4,
    "image": "../assets/skincare/skincare4.jpeg"
  },
  {
    "id": 5,
    "image": "../assets/skincare/skincare5.jpeg"
  },
  {
    "id": 6,
    "image": "../assets/skincare/skincare6.jpeg"
  },
  {
    "id": 7,
    "image": "../assets/skincare/skincare7.jpeg"
  },
  {
    "id": 8,
    "image": "../assets/skincare/skincare8.jpeg"
  },
  {
    "id": 9,
    "image": "../assets/skincare/skincare9.jpeg"
  },
  {
    "id": 10,
    "image": "../assets/skincare/skincare10.jpeg"
  },
  {
    "id": 11,
    "image": "../assets/skincare/skincare11.jpeg"
  },
  {
    "id": 12,
    "image": "../assets/skincare/skincare12.jpeg"
  },
  {
    "id": 13,
    "image": "../assets/skincare/skincare13.jpeg"
  },
  {
    "id": 14,
    "image": "../assets/skincare/skincare14.jpeg"
  },
  {
    "id": 15,
    "image": "../assets/skincare/skincare15.jpeg"
  },
  {
    "id": 16,
    "image": "../assets/skincare/skincare16.jpeg"
  },
  {
    "id": 17,
    "image": "../assets/skincare/skincare17.jpeg"
  },
  {
    "id": 18,
    "image": "../assets/skincare/skincare18.jpeg"
  },
  {
    "id": 19,
    "image": "../assets/skincare/skincare19.jpeg"
  },
  {
    "id": 20,
    "image": "../assets/skincare/skincare20.jpeg"
  },
  {
    "id": 21,
    "image": "../assets/skincare/skincare21.jpeg"
  },
  {
    "id": 22,
    "image": "../assets/skincare/skincare22.jpeg"
  },
  {
    "id": 23,
    "image": "../assets/skincare/skincare23.jpeg"
  },
  {
    "id": 24,
    "image": "../assets/skincare/skincare24.jpeg"
  },
  {
    "id": 25,
    "image": "../assets/skincare/skincare25.jpeg"
  },
  {
    "id": 26,
    "image": "../assets/skincare/skincare26.jpeg"
  },
  {
    "id": 27,
    "image": "../assets/skincare/skincare27.jpeg"
  },
  {
    "id": 28,
    "image": "../assets/skincare/skincare28.jpeg"
  },
  {
    "id": 29,
    "image": "../assets/skincare/skincare29.jpeg"
  },
  {
    "id": 30,
    "image": "../assets/skincare/skincare30.jpeg"
  },
  {
    "id": 31,
    "image": "../assets/skincare/skincare31.jpeg"
  },
  {
    "id": 32,
    "image": "../assets/skincare/skincare32.jpeg"
  },
  {
    "id": 33,
    "image": "../assets/skincare/skincare33.jpeg"
  },
  {
    "id": 34,
    "image": "../assets/skincare/skincare34.jpeg"
  },
  {
    "id": 35,
    "image": "../assets/skincare/skincare35.jpeg"
  },
  {
    "id": 36,
    "image": "../assets/skincare/skincare36.jpeg"
  },
  {
    "id": 37,
    "image": "../assets/skincare/skincare37.jpeg"
  },
  {
    "id": 38,
    "image": "../assets/skincare/skincare39.jpeg"
  },
  {
    "id": 39,
    "image": "../assets/skincare/skincare40.jpeg"
  },
  {
    "id": 40,
    "image": "../assets/skincare/skincare41.jpeg"
  },
  {
    "id": 41,
    "image": "../assets/skincare/skincare48.jpeg"
  },
  {
    "id": 42,
    "image": "../assets/skincare/skincare49.jpeg"
  },
  {
    "id": 43,
    "image": "../assets/skincare/skincare50.jpeg"
  },
  {
    "id": 44,
    "image": "../assets/skincare/skincare51.jpeg"
  },
  {
    "id": 45,
    "image": "../assets/skincare/skincare52.jpeg"
  },
  {
    "id": 46,
    "image": "../assets/skincare/skincare53.jpeg"
  },
  {
    "id": 47,
    "image": "../assets/skincare/skincare54.jpeg"
  },
  {
    "id": 48,
    "image": "../assets/skincare/skincare55.jpeg"
  },
  {
    "id": 49,
    "image": "../assets/skincare/skincare56.jpeg"
  },
  {
    "id": 50,
    "image": "../assets/skincare/skincare57.jpeg"
  },
  {
    "id": 51,
    "image": "../assets/skincare/skincare58.jpeg"
  },
  {
    "id": 52,
    "image": "../assets/skincare/skincare59.jpeg"
  },
  {
    "id": 53,
    "image": "../assets/skincare/skincare60.jpeg"
  },
  {
    "id": 54,
    "image": "../assets/skincare/skincare61.jpeg"
  },
  {
    "id": 55,
    "image": "../assets/skincare/skincare62.jpeg"
  },
  {
    "id": 56,
    "image": "../assets/skincare/skincare63.jpeg"
  },
  {
    "id": 57,
    "image": "../assets/skincare/skincare64.jpeg"
  },
  {
    "id": 58,
    "image": "../assets/skincare/skincare65.jpeg"
  },
  {
    "id": 59,
    "image": "../assets/skincare/skincare66.jpeg"
  },
  {
    "id": 60,
    "image": "../assets/skincare/skincare67.jpeg"
  },
  {
    "id": 61,
    "image": "../assets/skincare/skincare68.jpeg"
  },
  {
    "id": 62,
    "image": "../assets/skincare/skincare69.jpeg"
  },
  {
    "id": 63,
    "image": "../assets/skincare/skincare70.jpeg"
  },
  {
    "id": 64,
    "image": "../assets/skincare/skincare71.jpeg"
  },
  {
    "id": 65,
    "image": "../assets/skincare/skincare72.jpeg"
  },
  {
    "id": 66,
    "image": "../assets/skincare/skincare73.jpeg"
  },
  {
    "id": 67,
    "image": "../assets/skincare/74.jpeg"
  },
  {
    "id": 68,
    "image": "../assets/skincare/75.jpeg"
  },
  {
    "id": 69,
    "image": "../assets/skincare/76.jpeg"
  },
  {
    "id": 70,
    "image": "../assets/skincare/78.jpeg"
  },
  {
    "id": 71,
    "image": "../assets/skincare/79.jpeg"
  },
  {
    "id": 72,
    "image": "../assets/skincare/80.jpeg"
  },
  {
    "id": 73,
    "image": "../assets/skincare/82.jpeg"
  },
  {
    "id": 74,
    "image": "../assets/skincare/83.jpeg"
  },
  {
    "id": 75,
    "image": "../assets/skincare/84.jpeg"
  },
  {
    "id": 76,
    "image": "../assets/skincare/85.jpeg"
  },
  {
    "id": 77,
    "image": "../assets/skincare/86.jpeg"
  },
  {
    "id": 78,
    "image": "../assets/skincare/87.jpeg"
  },
  {
    "id": 79,
    "image": "../assets/skincare/88.jpeg"
  },
  {
    "id": 80,
    "image": "../assets/skincare/89.jpeg"
  },
  {
    "id": 81,
    "image": "../assets/skincare/90.jpeg"
  },
  {
    "id": 82,
    "image": "../assets/skincare/91.jpeg"
  },
  {
    "id": 83,
    "image": "../assets/skincare/92.jpeg"
  },
  {
    "id": 84,
    "image": "../assets/skincare/93.jpeg"
  },
  {
    "id": 85,
    "image": "../assets/skincare/94.jpeg"
  },
  {
    "id": 86,
    "image": "../assets/skincare/95.jpeg"
  },
  {
    "id": 87,
    "image": "../assets/skincare/96.jpeg"
  },
  {
    "id": 88,
    "image": "../assets/skincare/97.jpeg"
  },
  {
    "id": 89,
    "image": "../assets/skincare/98.jpeg"
  }
]